adamalib/__init__.py
adamalib/adamalib.py
adamalib-0.1.0.data/data/requirements.txt
adamalib-0.1.0.dist-info/DESCRIPTION.rst
adamalib-0.1.0.dist-info/METADATA
adamalib-0.1.0.dist-info/RECORD
adamalib-0.1.0.dist-info/WHEEL
adamalib-0.1.0.dist-info/metadata.json
adamalib-0.1.0.dist-info/top_level.txt
