Metadata-Version: 2.0
Name: adamalib
Version: 0.1.0
Summary: Adama Library
Home-page: https://github.com/Arabidopsis-Information-Portal/adamalib
Author: John Gentle
Author-email: jgentle@tacc.utexas.edu
License: BSD
Download-URL: https://github.com/Arabidopsis-Information-Portal/adamalib
Keywords: adamalib
Platform: UNKNOWN
Classifier: Development Status :: 2 - Pre-Alpha
Classifier: Intended Audience :: Developers
Classifier: License :: OSI Approved :: BSD License
Classifier: Natural Language :: English
Classifier: Programming Language :: Python :: 2
Classifier: Programming Language :: Python :: 2.6
Classifier: Programming Language :: Python :: 2.7
Classifier: Programming Language :: Python :: 3
Classifier: Programming Language :: Python :: 3.3
Requires-Dist: PyYAML (==3.11)
Requires-Dist: decorator (==3.4.2)
Requires-Dist: lxml (==3.4.4)
Requires-Dist: networkx (==1.9.1)
Requires-Dist: prov (==1.3.1)
Requires-Dist: py (==1.4.26)
Requires-Dist: pytest (==2.6.4)
Requires-Dist: python-dateutil (==2.4.2)
Requires-Dist: requests (==2.6.0)
Requires-Dist: six (==1.9.0)
Requires-Dist: wheel (==0.24.0)
